jupyterlab_commands/__init__.py
jupyterlab_commands/_version.py
jupyterlab_commands/extension.py
jupyterlab_commands/extension/jupyterlab_commands.json
jupyterlab_commands/labextension/package.json
jupyterlab_commands/labextension/static/568.6fa7c06d94b5d4c0a342.js
jupyterlab_commands/labextension/static/873.af0a6b8becacd1ba8457.js
jupyterlab_commands/labextension/static/remoteEntry.94043ea2257c211ef483.js
jupyterlab_commands/labextension/static/style.js
jupyterlab_commands/labextension/static/third-party-licenses.json
jupyterlab_commands/tests/__init__.py
jupyterlab_commands/tests/test_all.py
jupyterlab_commands/tests/test_extension.py
jupyterlab_commands/tests/test_init.py
jupyterlab_commands-0.4.0.data/data/etc/jupyter/jupyter_server_config.d/jupyterlab_commands.json
jupyterlab_commands-0.4.0.data/data/share/jupyter/labextensions/jupyterlab_commands/package.json
jupyterlab_commands-0.4.0.data/data/share/jupyter/labextensions/jupyterlab_commands/static/568.6fa7c06d94b5d4c0a342.js
jupyterlab_commands-0.4.0.data/data/share/jupyter/labextensions/jupyterlab_commands/static/873.af0a6b8becacd1ba8457.js
jupyterlab_commands-0.4.0.data/data/share/jupyter/labextensions/jupyterlab_commands/static/remoteEntry.94043ea2257c211ef483.js
jupyterlab_commands-0.4.0.data/data/share/jupyter/labextensions/jupyterlab_commands/static/style.js
jupyterlab_commands-0.4.0.data/data/share/jupyter/labextensions/jupyterlab_commands/static/third-party-licenses.json
jupyterlab_commands-0.4.0.dist-info/METADATA
jupyterlab_commands-0.4.0.dist-info/WHEEL
jupyterlab_commands-0.4.0.dist-info/licenses/LICENSE
jupyterlab_commands-0.4.0.dist-info/RECORD
